njoy/CMakeLists.txt
njoy/LICENSE
njoy/entrypoint.py
njoy/bin/njoy
njoy/lib/libnjoy.a
njoy/src/acecm.f90
njoy/src/acedo.f90
njoy/src/acefc.f90
njoy/src/acepa.f90
njoy/src/acepn.f90
njoy/src/acer.f90
njoy/src/aceth.f90
njoy/src/broadr.f90
njoy/src/ccccr.f90
njoy/src/covr.f90
njoy/src/dtfr.f90
njoy/src/endf.f90
njoy/src/errorr.f90
njoy/src/gaminr.f90
njoy/src/gaspr.f90
njoy/src/graph.f90
njoy/src/groupr.f90
njoy/src/heatr.f90
njoy/src/leapr.f90
njoy/src/locale.f90
njoy/src/main.f90
njoy/src/mainio.f90
njoy/src/mathm.f90
njoy/src/matxsr.f90
njoy/src/mixr.f90
njoy/src/moder.f90
njoy/src/phys.f90
njoy/src/plotr.f90
njoy/src/powr.f90
njoy/src/purr.f90
njoy/src/reconr.f90
njoy/src/resxsr.f90
njoy/src/samm.f90
njoy/src/thermr.f90
njoy/src/unresr.f90
njoy/src/util.f90
njoy/src/vers.f90
njoy/src/viewr.f90
njoy/src/wimsr.f90
njoy-2016.78.dist-info/METADATA
njoy-2016.78.dist-info/WHEEL
njoy-2016.78.dist-info/entry_points.txt
njoy-2016.78.dist-info/top_level.txt
njoy-2016.78.dist-info/RECORD
